{
  "generatedAt": "2026-06-05T08:04:00.133Z",
  "source": "mixpanel",
  "status": "ok",
  "dailyVisitors": [
    {
      "date": "2026-05-30",
      "visitors": 3
    },
    {
      "date": "2026-05-31",
      "visitors": 3
    },
    {
      "date": "2026-06-01",
      "visitors": 3
    },
    {
      "date": "2026-06-02",
      "visitors": 1
    },
    {
      "date": "2026-06-03",
      "visitors": 1
    },
    {
      "date": "2026-06-04",
      "visitors": 2
    },
    {
      "date": "2026-06-05",
      "visitors": 1
    }
  ],
  "weeklyVisitors": {
    "visitors": 8,
    "visits": 395
  },
  "activeNow": 0,
  "topCities": [
    {
      "name": "Incheon",
      "count": 289
    },
    {
      "name": "Ansan-si",
      "count": 88
    },
    {
      "name": "Thrissur",
      "count": 13
    },
    {
      "name": "Gimpo-si",
      "count": 3
    }
  ],
  "topCountries": [
    {
      "name": "KR",
      "count": 382
    },
    {
      "name": "IN",
      "count": 13
    }
  ],
  "topPages": [
    {
      "name": "/",
      "count": 53
    },
    {
      "name": "/chrono/2026-05-30",
      "count": 31
    },
    {
      "name": "/timeline/2026-05-30",
      "count": 29
    },
    {
      "name": "/timeline/2026-06-01",
      "count": 26
    },
    {
      "name": "/chrono/2026-05-29",
      "count": 25
    }
  ],
  "topReferrers": [
    {
      "name": "t.co",
      "count": 14
    },
    {
      "name": "self-track-zeta.vercel.app",
      "count": 8
    }
  ]
}